<?xml version="1.0" encoding="UTF-8"?>
<Solution>
    <MetaData>
        <SolutionName>./Repository/TravelOptimization/Solutions/NL14HistSol_13_5_2004.xml</SolutionName>
        <InstanceName>./Repository/TravelOptimization/Instances/NL14.xml</InstanceName>
        <Contributor>Anagnostopoulos, Michel, Van Hentenryck and Vergados</Contributor>
        <Date year="2004" month="5" day="13"/>
        <SolutionMethod>NULL</SolutionMethod>
        <ObjectiveValue infeasibility="0" objective="189766"/>
        <Remarks>NULL</Remarks>
    </MetaData>
    <Games/>
</Solution>
